drf_jwt/__init__.py
drf_jwt/authentication.py
drf_jwt/controllers.py
drf_jwt/validators.py
django_rest_jwt-0.1.44.dist-info/LICENSE
django_rest_jwt-0.1.44.dist-info/METADATA
django_rest_jwt-0.1.44.dist-info/WHEEL
django_rest_jwt-0.1.44.dist-info/top_level.txt
django_rest_jwt-0.1.44.dist-info/RECORD
