Metadata-Version: 2.1
Name: django-rest-jwt
Version: 0.1.44
Summary: simple JWT handling for django REST Framework
Home-page: https://github.com/Pythux/drf-jwt
Author: Pythux
License: UNKNOWN
Platform: UNKNOWN
Classifier: Programming Language :: Python :: 3
Classifier: License :: OSI Approved :: MIT License
Classifier: Operating System :: OS Independent
Classifier: Environment :: Web Environment
Classifier: Framework :: Django
Classifier: Intended Audience :: Developers
Classifier: Programming Language :: Python :: 3
Classifier: Topic :: Internet :: WWW/HTTP
Requires-Python: >=3.6
Requires-Dist: PyJWT (<2.0.0,>=1.5.2)
